{
  "original_file": "src\\dojopool\\static\\js\\leaderboard.js",
  "typescript_file": "src\\dojopool\\static\\js\\leaderboard.ts",
  "backup_file": "src\\dojopool\\backups\\js_migration\\leaderboard.js",
  "analysis": {
    "functions": [],
    "classes": [
      {
        "name": "LeaderboardManager",
        "extends": null,
        "properties": []
      }
    ],
    "variables": [
      {
        "name": "category",
        "type": "any"
      },
      {
        "name": "response",
        "type": "any"
      },
      {
        "name": "data",
        "type": "any"
      },
      {
        "name": "tableBody",
        "type": "any"
      },
      {
        "name": "row",
        "type": "any"
      },
      {
        "name": "alertDiv",
        "type": "any"
      }
    ],
    "imports": [],
    "exports": []
  },
  "generated_types": {
    "LeaderboardManager": "\nclass LeaderboardManager {\n    // Properties and methods\n}"
  }
}